mwman.py
mwman/MWMan.php
mwman/__init__.py
mwman/__main__.py
mwman/application.py
mwman/mwman.py
mwman-0.1.dist-info/LICENSE
mwman-0.1.dist-info/METADATA
mwman-0.1.dist-info/WHEEL
mwman-0.1.dist-info/entry_points.txt
mwman-0.1.dist-info/top_level.txt
mwman-0.1.dist-info/RECORD
